Workbook

Sheet Capex and Depreciation Schedule
A1: Capex & Depreciation | B1: Useful Life (Years) | C1: Year 1 | D1: Year 2 | E1: Year 3 | F1: Year 4
A3: Capex
A4: Laptops | B4: 5 | C4: 50000
A5: Custom Software Apps | B5: 3 | C5: 50000 | D5: 100000 | E5: 100000
A6: New Ovens | B6: 5 | E6: 30000
A7: Total Capex | C7: =SUM(C3:C6) -> 100000 | D7: =SUM(D3:D6) -> 100000 | E7: =SUM(E3:E6) -> 130000 | F7: =SUM(F3:F6) -> 0
A9: Depreciation
A10: Laptops | C10: =$C$4/$B$4 -> 10000 | D10: =$C$4/$B$4 -> 10000 | E10: =$C$4/$B$4 -> 10000 | F10: =$C$4/$B$4 -> 10000
A11: Custom Software Apps | C11: =$C$5/$B$5 -> 16666.667 | D11: =$C$5/$B$5+$D$5/$B$5 -> 50000 | E11: =$C$5/$B$5+$D$5/$B$5+$E$5/$B$5 -> 83333.333 | F11: =$D$5/$B$5+$E$5/$B$5 -> 66666.667
A12: New Ovens | E12: =$E$6/$B$6 -> 6000 | F12: =$E$6/$B$6 -> 6000
A13: Total D&A (Depreciation & Amortization) | C13: =SUM(C10:C12) -> 26666.667 | D13: =SUM(D10:D12) -> 60000 | E13: =SUM(E10:E12) -> 99333.333 | F13: =SUM(F10:F12) -> 82666.667

Sheet Income Statement 
A1: Mail Order Cookie Company | I1: Mail Order Cookie Company
A2: Income Statement | B2: 1st Year | C2: 2nd Year | D2: 3rd Year | E2: 4th Year | I2: Income Statement | J2: 1st Year | K2: 2nd Year | L2: 3rd Year | M2: 4th Year
A4: MY ASSUMPTIONS | I4: Revenue
A6: Revenue | I6: Gross Revenue | J6: =B7*B8 -> 1750000 | K6: =C7*C8 -> 2750000 | L6: =D7*D8 -> 5500000 | M6: =E7*E8 -> 11250000
A7: New Customers | B7: 70000 | C7: 110000 | D7: 220000 | E7: 450000 | I7: Refunds | J7: =-J$6*B9 -> -87500 | K7: =-K$6*C9 -> -137500 | L7: =-L$6*D9 -> -275000 | M7: =-M$6*E9 -> -562500
A8: AOV (Average Order Value) | B8: 25 | C8: 25 | D8: 25 | E8: 25 | I8: Discounts | J8: =-J$6*B10 -> -140000 | K8: =-K$6*C10 -> -220000 | L8: =-L$6*D10 -> -440000 | M8: =-M$6*E10 -> -900000
A9: Refunds (as % revenue) | B9: 0.05 | C9: 0.05 | D9: 0.05 | E9: 0.05 | I9: Net Revenues | J9: =SUM(J6:J8) -> 1522500 | K9: =SUM(K6:K8) -> 2392500 | L9: =SUM(L6:L8) -> 4785000 | M9: =SUM(M6:M8) -> 9787500
A10: Discounts | B10: 0.08 | C10: 0.08 | D10: 0.08 | E10: 0.08
I11: COGS (Cost of goods sold)
A12: COGS (Cost of Goods Sold) | I12: Product (Material Cost) | J12: =J$9*B13 -> 456750 | K12: =K$9*C13 -> 717750 | L12: =L$9*D13 -> 1435500 | M12: =M$9*E13 -> 2936250
A13: Product (Materials cost) | B13: 0.3 | C13: 0.3 | D13: 0.3 | E13: 0.3 | I13: Fullfillment | J13: =J$9*B14 -> 106575 | K13: =K$9*C14 -> 167475 | L13: =L$9*D14 -> 334950 | M13: =M$9*E14 -> 685125
A14: Fullfillment | B14: 0.07 | C14: 0.07 | D14: 0.07 | E14: 0.07 | I14: Merchant Services | J14: =J$9*B15 -> 152250 | K14: =K$9*C15 -> 239250 | L14: =L$9*D15 -> 478500 | M14: =M$9*E15 -> 978750
A15: Merchant Services | B15: 0.1 | C15: 0.1 | D15: 0.1 | E15: 0.1 | I15: Total COGS | J15: =SUM(J12:J14) -> 715575 | K15: =SUM(K12:K14) -> 1124475 | L15: =SUM(L12:L14) -> 2248950 | M15: =SUM(M12:M14) -> 4600125
A17: Operating Expenses | I17: Gross Margin | J17: =J9-J15 -> 806925 | K17: =K9-K15 -> 1268025 | L17: =L9-L15 -> 2536050 | M17: =M9-M15 -> 5187375
A18: HR | B18: 0.25 | C18: 0.25 | D18: 0.25 | E18: 0.25 | I18: GM % | J18: =J17/J9 -> 0.53 | K18: =K17/K9 -> 0.53 | L18: =L17/L9 -> 0.53 | M18: =M17/M9 -> 0.53
A19: Marketing | B19: 0.1 | C19: 0.1 | D19: 0.1 | E19: 0.1
A20: Misc | B20: 0.05 | C20: 0.05 | D20: 0.05 | E20: 0.05 | I20: Operating Expenses
A21: Depreciation (other model) | I21: HR | J21: =J$9*B18 -> 380625 | K21: =K$9*C18 -> 598125 | L21: =L$9*D18 -> 1196250 | M21: =M$9*E18 -> 2446875
I22: Marketing | J22: =J$9*B19 -> 152250 | K22: =K$9*C19 -> 239250 | L22: =L$9*D19 -> 478500 | M22: =M$9*E19 -> 978750
A23: Interest on Debt (other model) | I23: Misc | J23: =J$9*B20 -> 76125 | K23: =K$9*C20 -> 119625 | L23: =L$9*D20 -> 239250 | M23: =M$9*E20 -> 489375
I24: Depreciation (other model) | J24: ='Capex and Depreciation Schedule'!C13 -> 26666.667 | K24: ='Capex and Depreciation Schedule'!D13 -> 60000 | L24: ='Capex and Depreciation Schedule'!E13 -> 99333.333 | M24: ='Capex and Depreciation Schedule'!F13 -> 82666.667
A25: Tax Rate | B25: 0.22 | C25: 0.22 | D25: 0.22 | E25: 0.22 | I25: Total Operating Expenses | J25: =SUM(J20:J24) -> 635666.67 | K25: =SUM(K20:K24) -> 1017000 | L25: =SUM(L20:L24) -> 2013333.3 | M25: =SUM(M20:M24) -> 3997666.7
I27: Operating Income | J27: =J17-J25 -> 171258.33 | K27: =K17-K25 -> 251025 | L27: =L17-L25 -> 522716.67 | M27: =M17-M25 -> 1189708.3
I29: Interest (other model) | J29: ='Balance sheet'!C45 -> 175000 | K29: ='Balance sheet'!D45 -> 196000 | L29: ='Balance sheet'!E45 -> 147000 | M29: ='Balance sheet'!F45 -> 98000
I31: NI (Net Income) Before Tax | J31: =J27-J29 -> -3741.6667 | K31: =K27-K29 -> 55025 | L31: =L27-L29 -> 375716.67 | M31: =M27-M29 -> 1091708.3
I33: Taxes | J33: =J31*B25 -> -823.16667 | K33: =K31*C25 -> 12105.5 | L33: =L31*D25 -> 82657.667 | M33: =M31*E25 -> 240175.83
I35: Net Income | J35: =J31-J33 -> -2918.5 | K35: =K31-K33 -> 42919.5 | L35: =L31-L33 -> 293059 | M35: =M31-M33 -> 851532.5
I36: NI% | J36: =J35/J9 -> -0.001916913 | K36: =K35/K9 -> 0.017939185 | L36: =L35/L9 -> 0.06124535 | M36: =M35/M9 -> 0.087002043
I38: EBITDA | J38: =J27+J24 -> 197925 | K38: =K27+K24 -> 311025 | L38: =L27+L24 -> 622050 | M38: =M27+M24 -> 1272375

Sheet Balance sheet
A1: Balance Sheet | B1: Dec 31-Year 0 | C1: Year 1 | D1: Year 2 | E1: Year 3 | F1: Year 4
B2: Historicals
A3: ASSETS
A5: Cash | B5: 4250000 | C5: =B5+'Cashflow statement'!B22 -> 3754648.7 | D5: =C5+'Cashflow statement'!C22 -> 4116293.7 | E5: =D5+'Cashflow statement'!D22 -> 3846161 | F5: =E5+'Cashflow statement'!E22 -> 4674135.7
A6: Account Receivable (AR) | B6: 120000 | C6: =C37*C38 -> 76125 | D6: =D37*D38 -> 119625 | E6: =E37*E38 -> 239250 | F6: =F37*F38 -> 489375
A7: Total Current Assets | B7: =SUM(B5:B6) -> 4370000 | C7: =SUM(C5:C6) -> 3830773.7 | D7: =SUM(D5:D6) -> 4235918.7 | E7: =SUM(E5:E6) -> 4085411 | F7: =SUM(F5:F6) -> 5163510.7
A9: Fixed Assets | B9: 40000 | C9: ='Balance sheet'!B9+'Capex and Depreciation Schedule'!C7 -> 140000 | D9: ='Balance sheet'!C9+'Capex and Depreciation Schedule'!D7 -> 240000 | E9: ='Balance sheet'!D9+'Capex and Depreciation Schedule'!E7 -> 370000 | F9: ='Balance sheet'!E9+'Capex and Depreciation Schedule'!F7 -> 370000
A10: Accumulated Depreciation | B10: -10000 | C10: =B10-'Capex and Depreciation Schedule'!C13 -> -36666.667 | D10: =C10-'Capex and Depreciation Schedule'!D13 -> -96666.667 | E10: =D10-'Capex and Depreciation Schedule'!E13 -> -196000 | F10: =E10-'Capex and Depreciation Schedule'!F13 -> -278666.67
A11: Net Fixed Assets | B11: =SUM(B9:B10) -> 30000 | C11: =SUM(C9:C10) -> 103333.33 | D11: =SUM(D9:D10) -> 143333.33 | E11: =SUM(E9:E10) -> 174000 | F11: =SUM(F9:F10) -> 91333.333
A13: Total Assets | B13: =B7+B11 -> 4400000 | C13: =C7+C11 -> 3934107 | D13: =D7+D11 -> 4379252 | E13: =E7+E11 -> 4259411 | F13: =F7+F11 -> 5254844
A15: LIABILITIES
A17: Accounts Payable (AP) | B17: 75000 | C17: =C37*C39 -> 91350 | D17: =D37*D39 -> 143550 | E17: =E37*E39 -> 287100 | F17: =F37*F39 -> 587250
A18: Deferred Revenue | B18: 25000 | C18: =C37*C40 -> 45675 | D18: =D37*D40 -> 95700 | E18: =E37*E40 -> 239250 | F18: =F37*F40 -> 783000
A19: Total Current Assets | B19: =SUM(B17:B18) -> 100000 | C19: =SUM(C17:C18) -> 137025 | D19: =SUM(D17:D18) -> 239250 | E19: =SUM(E17:E18) -> 526350 | F19: =SUM(F17:F18) -> 1370250
A21: Long Term Debt | B21: 3000000 | C21: =B21+C42-C43 -> 2500000 | D21: =C21+D42-D43 -> 2800000 | E21: =D21+E42-E43 -> 2100000 | F21: =E21+F42-F43 -> 1400000
A23: Total Liabilities | B23: =B19+B21 -> 3100000 | C23: =C19+C21 -> 2637025 | D23: =D19+D21 -> 3039250 | E23: =E19+E21 -> 2626350 | F23: =F19+F21 -> 2770250
A25: EQUITY
A27: Common Stock | B27: 50000 | C27: =B27 -> 50000 | D27: =C27 -> 50000 | E27: =D27 -> 50000 | F27: =E27 -> 50000
A28: Retained Earnings | B28: 1250000 | C28: =B28+'Income Statement '!J35 -> 1247081.5 | D28: =C28+'Income Statement '!K35 -> 1290001 | E28: =D28+'Income Statement '!L35 -> 1583060 | F28: =E28+'Income Statement '!M35 -> 2434592.5
A29: Total Shareholders Equity | B29: =SUM(B27:B28) -> 1300000 | C29: =SUM(C27:C28) -> 1297081.5 | D29: =SUM(D27:D28) -> 1340001 | E29: =SUM(E27:E28) -> 1633060 | F29: =SUM(F27:F28) -> 2484592.5
A31: Liabilities & Shareholders Equity | B31: =B23+B29 -> 4400000 | C31: =C23+C29 -> 3934106.5 | D31: =D23+D29 -> 4379251 | E31: =E23+E29 -> 4259410 | F31: =F23+F29 -> 5254842.5
A33: Balance Check | B33: =B13-B31 -> 0 | C33: =C13-C31 -> 0.5 | D33: =D13-D31 -> 1 | E33: =E13-E31 -> 1 | F33: =F13-F31 -> 1.5
A35: ASSUMPTIONS
A37: Net Revenue | C37: ='Income Statement '!J9 -> 1522500 | D37: ='Income Statement '!K9 -> 2392500 | E37: ='Income Statement '!L9 -> 4785000 | F37: ='Income Statement '!M9 -> 9787500
A38: AR (% of revenue) | C38: 0.05 | D38: 0.05 | E38: 0.05 | F38: 0.05
A39: AP (% of revenue) | C39: 0.06 | D39: 0.06 | E39: 0.06 | F39: 0.06
A40: Deferred Revenue | C40: 0.03 | D40: 0.04 | E40: 0.05 | F40: 0.08
A42: Net Borrowing (New Debt Taken On) | D42: 1000000
A43: Debt Payments | C43: 500000 | D43: 700000 | E43: 700000 | F43: 700000
A44: Interest Rate | C44: 0.07 | D44: 0.07 | E44: 0.07 | F44: 0.07
A45: Interest Payments | C45: =C21*C44 -> 175000 | D45: =D21*D44 -> 196000 | E45: =E21*E44 -> 147000 | F45: =F21*F44 -> 98000

Sheet Cashflow statement
A1: Cash Flow Statement | B1: 1st Year | C1: 2nd Year | D1: 3rd Year | E1: 4th Year
A3: Net Income | B3: -2918 | C3: 42920 | D3: 293059 | E3: 851533
A5: Operating Activities
A6: Depreciations | B6: ='Capex and Depreciation Schedule'!C13 -> 26666.667 | C6: ='Capex and Depreciation Schedule'!D13 -> 60000 | D6: ='Capex and Depreciation Schedule'!E13 -> 99333.333 | E6: ='Capex and Depreciation Schedule'!F13 -> 82666.667
A7: Change in AR | B7: ='Balance sheet'!B6-'Balance sheet'!C6 -> 43875 | C7: ='Balance sheet'!C6-'Balance sheet'!D6 -> -43500 | D7: ='Balance sheet'!D6-'Balance sheet'!E6 -> -119625 | E7: ='Balance sheet'!E6-'Balance sheet'!F6 -> -250125
A8: Change in AP | B8: ='Balance sheet'!C17-'Balance sheet'!B17 -> 16350 | C8: ='Balance sheet'!D17-'Balance sheet'!C17 -> 52200 | D8: ='Balance sheet'!E17-'Balance sheet'!D17 -> 143550 | E8: ='Balance sheet'!F17-'Balance sheet'!E17 -> 300150
A9: Change in Def Rev | B9: ='Balance sheet'!C18-'Balance sheet'!B18 -> 20675 | C9: ='Balance sheet'!D18-'Balance sheet'!C18 -> 50025 | D9: ='Balance sheet'!E18-'Balance sheet'!D18 -> 143550 | E9: ='Balance sheet'!F18-'Balance sheet'!E18 -> 543750
A10: Operating Cash Flow | B10: =B3+SUM(B6:B9) -> 104648.67 | C10: =C3+SUM(C6:C9) -> 161645 | D10: =D3+SUM(D6:D9) -> 559867.33 | E10: =E3+SUM(E6:E9) -> 1527974.7
A12: Investing Activities
A13: CapEx | B13: ='Capex and Depreciation Schedule'!C7 -> 100000 | C13: ='Capex and Depreciation Schedule'!D7 -> 100000 | D13: ='Capex and Depreciation Schedule'!E7 -> 130000 | E13: ='Capex and Depreciation Schedule'!F7 -> 0
A15: Free Cash Flow | B15: =B10-B13 -> 4648.6667 | C15: =C10-C13 -> 61645 | D15: =D10-D13 -> 429867.33 | E15: =E10-E13 -> 1527974.7 | G15: (op cashflow - Inv cashflow)
A17: Financing Activities
A18: Debt Repayment | B18: =-'Balance sheet'!C43 -> -500000 | C18: =-'Balance sheet'!D43 -> -700000 | D18: =-'Balance sheet'!E43 -> -700000 | E18: =-'Balance sheet'!F43 -> -700000
A19: Net Borrowings | B19: ='Balance sheet'!C42 -> 0 | C19: ='Balance sheet'!D42 -> 1000000 | D19: ='Balance sheet'!E42 -> 0 | E19: ='Balance sheet'!F42 -> 0
A20: NCF From Financing | B20: =SUM(B18:B19) -> -500000 | C20: =SUM(C18:C19) -> 300000 | D20: =SUM(D18:D19) -> -700000 | E20: =SUM(E18:E19) -> -700000
A22: Net cash Flow | B22: =B15+B20 -> -495351.33 | C22: =C15+C20 -> 361645 | D22: =D15+D20 -> -270132.67 | E22: =E15+E20 -> 827974.67
